{
  "participants": [
    {
      "id": "3684ce03-55f9-43e6-b261-32d5948a0f9f",
      "origin": "inhouse",
      "inhouseInvitationId": "189ea2fa-bbd0-4f2a-b6d1-e7edc890de91",
      "invoice": 1515,
      "membership": "233445",
      "reservationNumber": "2234",
      "coupleId": "5b59e1a4-58cb-43a0-b910-4c039681f15d",
      "persons": [
        {
          "id": "e5e5499d-9c39-4c83-b49f-1cee22ca27f2",
          "createdAt": "2022-02-10T16:52:08.455Z",
          "updatedAt": "2022-02-16T23:55:25.255Z",
          "active": true,
          "name": "Ricardo",
          "lastname": "Can",
          "code": "IX15920",
          "mail": "rcan@palaceresorts.com",
          "phone": "1234567890",
          "age": null,
          "tourAttended": true,
          "reference": null,
          "version": null
        },
        {
          "id": "f5e5499d-9c39-4c83-b49f-1cee22ca27f2",
          "createdAt": "2022-02-10T16:52:08.455Z",
          "updatedAt": "2022-02-16T23:55:25.255Z",
          "active": true,
          "name": "Rodolfo",
          "lastname": "Dzul",
          "code": "IX15920",
          "mail": "rdzul@palaceresorts.com",
          "phone": "1234567890",
          "age": null,
          "tourAttended": true,
          "reference": null,
          "version": null
        }
      ],
      "coupleStatus": "TOUR",
      "createdAt": "2022-07-08T23:24:14.671Z"
    },
    {
      "id": "189ea2fa-55f9-43e6-b261-32d5948a0f9f",
      "origin": "inhouse",
      "inhouseInvitationId": "986ea1fa-bbd0-4f2a-b6d1-e7edc890de78",
      "invoice": 1897,
      "membership": null,
      "reservationNumber": "8863",
      "coupleId": "6b42e1a4-58cb-43a0-b910-4c039681f15d",
      "persons": [
        {
          "id": "e5e5499d-9c39-4c83-b49f-1cee22ca27f2",
          "createdAt": "2022-02-10T16:52:08.455Z",
          "updatedAt": "2022-02-16T23:55:25.255Z",
          "active": true,
          "name": "Luis",
          "lastname": "Guerrero",
          "code": "IX15920",
          "mail": "luis.guerrero@palaceresorts.com",
          "phone": "0890273843",
          "age": null,
          "tourAttended": true,
          "reference": null,
          "version": null
        }
      ],
      "coupleStatus": "TOUR",
      "createdAt": "2022-07-08T23:24:14.671Z"
    },
    {
      "id": "297ea3fa-88f1-43e6-b261-32d5948a0f9f",
      "origin": "inhouse",
      "inhouseInvitationId": "666ea3fa-bbd1-4f2a-b6d1-e7edc890de78",
      "invoice": 1877,
      "membership": "7889879",
      "reservationNumber": "8822",
      "coupleId": "9b47e3a2-58cb-43a0-b910-4c039681f15d",
      "persons": [
        {
          "id": "e6e8877d-9c39-4c83-b49f-1cee22ca27f2",
          "createdAt": "2022-02-10T16:52:08.455Z",
          "updatedAt": "2022-02-16T23:55:25.255Z",
          "active": true,
          "name": "Christopher",
          "lastname": "Gerardy",
          "code": "IX15988",
          "mail": "chris.gerardy@palaceresorts.com",
          "phone": "9998881234",
          "age": null,
          "tourAttended": true,
          "reference": null,
          "version": null
        }
      ],
      "coupleStatus": "TOUR",
      "createdAt": "2022-07-08T23:24:14.671Z"
    }
  ]
}
